grapple/.gitignore
grapple/__init__.py
grapple/actions.py
grapple/apps.py
grapple/exceptions.py
grapple/helpers.py
grapple/middleware.py
grapple/models.py
grapple/registry.py
grapple/schema.py
grapple/settings.py
grapple/urls.py
grapple/utils.py
grapple/wagtail_hooks.py
grapple/migrations/0001_initial.py
grapple/migrations/0002_delete_pagepreview.py
grapple/migrations/0003_stubmodel.py
grapple/migrations/0004_delete_stubmodel.py
grapple/migrations/__init__.py
grapple/templates/grapple/graphiql.html
grapple/types/__init__.py
grapple/types/collections.py
grapple/types/documents.py
grapple/types/images.py
grapple/types/interfaces.py
grapple/types/media.py
grapple/types/pages.py
grapple/types/redirects.py
grapple/types/rich_text.py
grapple/types/search.py
grapple/types/settings.py
grapple/types/sites.py
grapple/types/snippets.py
grapple/types/streamfield.py
grapple/types/structures.py
grapple/types/tags.py
wagtail_grapple-0.29.0.dist-info/licenses/LICENSE
wagtail_grapple-0.29.0.dist-info/WHEEL
wagtail_grapple-0.29.0.dist-info/METADATA
wagtail_grapple-0.29.0.dist-info/RECORD
