Metadata-Version: 2.4
Name: wagtail-grapple
Version: 0.29.0
Summary: A Wagtail package that speeds up and simplifies implementing a GraphQL endpoint!
Keywords: wagtail,django,graphql,graphene,api
Author-email: Nathan Horrigan <hello@torchbox.com>
Maintainer-email: Dan Braghis <dan.braghis@torchbox.com>
Requires-Python: >=3.9
Classifier: Development Status :: 4 - Beta
Classifier: Intended Audience :: Developers
Classifier: License :: OSI Approved :: BSD License
Classifier: Operating System :: OS Independent
Classifier: Programming Language :: Python
Classifier: Programming Language :: Python :: 3
Classifier: Programming Language :: Python :: 3.9
Classifier: Programming Language :: Python :: 3.10
Classifier: Programming Language :: Python :: 3.11
Classifier: Programming Language :: Python :: 3.12
Classifier: Programming Language :: Python :: 3.13
Classifier: Framework :: Wagtail
Classifier: Framework :: Wagtail :: 6
Classifier: Framework :: Wagtail :: 7
License-File: LICENSE
Requires-Dist: Wagtail>=6.3
Requires-Dist: graphene-django>=3,<4
Requires-Dist: wagtail-headless-preview
Requires-Dist: Sphinx>=7.0,<8.0 ; extra == "docs"
Requires-Dist: sphinx-wagtail-theme>=6.0,<7.0 ; extra == "docs"
Requires-Dist: sphinxcontrib-spelling>=8.0,<9.0 ; extra == "docs"
Requires-Dist: sphinx_copybutton>=0.5 ; extra == "docs"
Requires-Dist: coverage>=7.2.7,<8.0 ; extra == "testing"
Requires-Dist: flit>=3.8 ; extra == "testing"
Requires-Dist: factory-boy==3.2.1 ; extra == "testing"
Requires-Dist: wagtail-factories>=4.1.0 ; extra == "testing"
Requires-Dist: django-cors-headers==3.4.0 ; extra == "testing"
Requires-Dist: wagtailmedia>=0.13 ; extra == "testing"
Requires-Dist: dj-database-url==2.1.0 ; extra == "testing"
Requires-Dist: psycopg2-binary>=2.9.5,<3.0.0 ; extra == "testing"
Project-URL: Changelog, https://github.com/torchbox/wagtail-grapple/blob/main/CHANGELOG.md
Project-URL: Documentation, https://wagtail-grapple.readthedocs.io/en/latest/
Provides-Extra: docs
Provides-Extra: testing
